udata_tabular_preview/__init__.py
udata_tabular_preview/explore.py
udata_tabular_preview/preview.py
udata_tabular_preview/settings.py
udata_tabular_preview/views.py
udata_tabular_preview/static/.gitignore
udata_tabular_preview/static/udata-tabular-preview/index-legacy.js
udata_tabular_preview/static/udata-tabular-preview/index.css
udata_tabular_preview/static/udata-tabular-preview/index.js
udata_tabular_preview/static/udata-tabular-preview/polyfills-legacy.js
udata_tabular_preview/templates/explore-button.html
udata_tabular_preview/templates/metadata.html
udata_tabular_preview/templates/script.html
udata_tabular_preview/templates/styles.html
udata_tabular_preview/translations/udata_tabular_preview.pot
udata_tabular_preview/translations/fr/LC_MESSAGES/udata_tabular_preview.mo
udata_tabular_preview/translations/fr/LC_MESSAGES/udata_tabular_preview.po
udata_tabular_preview-4.0.1.dist-info/METADATA
udata_tabular_preview-4.0.1.dist-info/WHEEL
udata_tabular_preview-4.0.1.dist-info/entry_points.txt
udata_tabular_preview-4.0.1.dist-info/top_level.txt
udata_tabular_preview-4.0.1.dist-info/RECORD
