Metadata-Version: 2.1
Name: udata-tabular-preview
Version: 4.0.1
Summary: A plugin to preview tabular files (CSV, Excel, ...) using tabular api
Home-page: https://github.com/opendatateam/udata-tabular-preview
Author: Open Data Team
Author-email: contact@opendata.team
License: AGPL
Keywords: udata,harvester,Tabular Preview
Classifier: Development Status :: 3 - Alpha
Classifier: Programming Language :: Python
Classifier: Environment :: Web Environment
Classifier: Operating System :: OS Independent
Classifier: Intended Audience :: Developers
Classifier: Topic :: System :: Software Distribution
Classifier: Programming Language :: Python
Classifier: Programming Language :: Python :: 3
Classifier: Programming Language :: Python :: 3.7
Classifier: Topic :: Software Development :: Libraries :: Python Modules
Requires-Python: >=3.7
Requires-Dist: udata >=4.0.0
Provides-Extra: test
Requires-Dist: mock ==3.0.5 ; extra == 'test'
Requires-Dist: pytest-flask ==1.2.0 ; extra == 'test'
Requires-Dist: pytest-sugar ==0.9.6 ; extra == 'test'
Requires-Dist: pytest ==7.2.1 ; extra == 'test'
